__init__.py
main.py
torchplite-0.1.1.dist-info/LICENSE
torchplite-0.1.1.dist-info/METADATA
torchplite-0.1.1.dist-info/WHEEL
torchplite-0.1.1.dist-info/top_level.txt
torchplite-0.1.1.dist-info/RECORD
