Metadata-Version: 2.1
Name: torchplite
Version: 0.1.1
Summary: A PyTorch implementation of the Planck 2018 Lite likelihood for the Cosmic Microwave Background (CMB) power spectra
Author-email: Benjamin Thorne <bn.thorne@gmail.com>
License: MIT License
Project-URL: homepage, https://github.com/bthorne93/torch-planck2018-lite
Project-URL: Source, https://github.com/bthorne93/torch-planck2018-lite
License-File: LICENSE
Requires-Dist: numpy
Requires-Dist: torch
Requires-Dist: scipy
